{
    "appKeys": {},
    "capabilities": [
        ""
    ],
    "companyName": "Glorious Edge",
    "longName": "Glorious Watch",
    "projectType": "native",
    "resources": {
        "media": [
            {
                "characterRegex": "[0-9a-zA-Z - : ]",
                "file": "fonts/imagine_font.ttf",
                "name": "FONT_IMAGINE_44",
                "type": "font"
            },
            {
                "characterRegex": "[a-zA-Z0-9 : , ' \\' ]",
                "file": "fonts/Roboto-Medium.ttf",
                "name": "FONT_ROBOTO_MEDIUM_30",
                "type": "font"
            },
            {
                "characterRegex": "[a-zA-Z0-9 :]",
                "file": "fonts/Roboto-Thin.ttf",
                "name": "FONT_ROBOTO_THIN_18",
                "type": "font"
            }
        ]
    },
    "sdkVersion": "3",
    "shortName": "Glorious",
    "targetPlatforms": [
        "basalt"
    ],
    "uuid": "6290fb46-51f4-42fc-bbec-878c06f07200",
    "versionLabel": "0.01",
    "watchapp": {
        "watchface": true
    }
}
